pysdt-0.1.2.dist-info/RECORD
pysdt-0.1.2.dist-info/WHEEL
pysdt-0.1.2.dist-info/METADATA
pysdt-0.1.2.dist-info/licenses/LICENSE
pysdt/_pysdt_impl.cpython-311-darwin.so
pysdt/__init__.py
