Metadata-Version: 2.1
Name: pysdt
Version: 0.1.2
Summary: A thin Python wrapper around the Sound Design Toolkit
Author-Email: David Marttila <david.marttila@gmail.com>
Classifier: License :: OSI Approved :: GNU General Public License v3 (GPLv3)
Classifier: Programming Language :: Python :: 3 :: Only
Classifier: Topic :: Multimedia :: Sound/Audio :: Sound Synthesis
Project-URL: Homepage, https://github.com/dsuedholt/pysdt
Requires-Python: >=3.10
Requires-Dist: numpy>=1.25
